Color/__init__.py
Color/koxs.py
Color/koxy.py
Open/__init__.py
Open/batch_operations.py
Open/core.py
Open/file_operations.py
Open/large_file_operations.py
Open/line_operations.py
Open/query_operations.py
Open/regex_operations.py
Open/text_operations.py
Open/undo_redo.py
Open/utils.py
koxs_Other_Operations/__init__.py
koxs_Other_Operations/koxs编码.py
koxs_Other_Operations/整理.py
koxs_terminal_tools-0.2.12.dist-info/licenses/LICENSE
koxs_terminal_tools-0.2.12.dist-info/METADATA
koxs_terminal_tools-0.2.12.dist-info/WHEEL
koxs_terminal_tools-0.2.12.dist-info/top_level.txt
koxs_terminal_tools-0.2.12.dist-info/RECORD
