Metadata-Version: 2.4
Name: koxs_terminal_tools
Version: 0.2.12
Summary: 一个功能强大的终端工具集合
Author: koxs
Author-email: 2931205209@qq.com
Project-URL: Bug Reports, https://github.com/koxs/koxs_terminal_tools/issues
Project-URL: Source, https://github.com/koxs/koxs_terminal_tools
Project-URL: Documentation, https://github.com/koxs/koxs_terminal_tools/wiki
Keywords: terminal,tools,file operations,color output,encoding,koxs
Classifier: Development Status :: 4 - Beta
Classifier: Intended Audience :: Developers
Classifier: License :: OSI Approved :: MIT License
Classifier: Operating System :: OS Independent
Classifier: Programming Language :: Python :: 3
Classifier: Programming Language :: Python :: 3.7
Classifier: Programming Language :: Python :: 3.8
Classifier: Programming Language :: Python :: 3.9
Classifier: Programming Language :: Python :: 3.10
Classifier: Programming Language :: Python :: 3.11
Classifier: Programming Language :: Python :: 3.12
Classifier: Topic :: Utilities
Classifier: Topic :: Software Development :: Libraries :: Python Modules
Requires-Python: >=3.7
License-File: LICENSE
Requires-Dist: pycryptodome>=3.10.1
Requires-Dist: cryptography>=3.4.8
Requires-Dist: chacha20>=0.1.0
Dynamic: author
Dynamic: author-email
Dynamic: classifier
Dynamic: description
Dynamic: description-content-type
Dynamic: keywords
Dynamic: license-file
Dynamic: project-url
Dynamic: requires-dist
Dynamic: requires-python
Dynamic: summary
